pycircstat2/__init__.py
pycircstat2/base.py
pycircstat2/clustering.py
pycircstat2/correlation.py
pycircstat2/descriptive.py
pycircstat2/distributions.py
pycircstat2/hypothesis.py
pycircstat2/regression.py
pycircstat2/utils.py
pycircstat2/version.py
pycircstat2/visualization.py
pycircstat2/data/fisher/B1.csv
pycircstat2/data/fisher/B1.csv-metadata.json
pycircstat2/data/fisher/B10.csv
pycircstat2/data/fisher/B10.csv-metadata.json
pycircstat2/data/fisher/B11.csv
pycircstat2/data/fisher/B11.csv-metadata.json
pycircstat2/data/fisher/B12.csv
pycircstat2/data/fisher/B12.csv-metadata.json
pycircstat2/data/fisher/B13.csv
pycircstat2/data/fisher/B13.csv-metadata.json
pycircstat2/data/fisher/B14.csv
pycircstat2/data/fisher/B14.csv-metadata.json
pycircstat2/data/fisher/B15.csv
pycircstat2/data/fisher/B15.csv-metadata.json
pycircstat2/data/fisher/B16.csv
pycircstat2/data/fisher/B16.csv-metadata.json
pycircstat2/data/fisher/B17.csv
pycircstat2/data/fisher/B17.csv-metadata.json
pycircstat2/data/fisher/B18.csv
pycircstat2/data/fisher/B18.csv-metadata.json
pycircstat2/data/fisher/B19.csv
pycircstat2/data/fisher/B19.csv-metadata.json
pycircstat2/data/fisher/B2.csv
pycircstat2/data/fisher/B2.csv-metadata.json
pycircstat2/data/fisher/B20.csv
pycircstat2/data/fisher/B20.csv-metadata.json
pycircstat2/data/fisher/B21.csv
pycircstat2/data/fisher/B21.csv-metadata.json
pycircstat2/data/fisher/B22.csv
pycircstat2/data/fisher/B22.csv-metadata.json
pycircstat2/data/fisher/B23.csv
pycircstat2/data/fisher/B23.csv-metadata.json
pycircstat2/data/fisher/B24.csv
pycircstat2/data/fisher/B24.csv-metadata.json
pycircstat2/data/fisher/B3.csv
pycircstat2/data/fisher/B3.csv-metadata.json
pycircstat2/data/fisher/B4.csv
pycircstat2/data/fisher/B4.csv-metadata.json
pycircstat2/data/fisher/B5.csv
pycircstat2/data/fisher/B5.csv-metadata.json
pycircstat2/data/fisher/B6.csv
pycircstat2/data/fisher/B6.csv-metadata.json
pycircstat2/data/fisher/B7.csv
pycircstat2/data/fisher/B7.csv-metadata.json
pycircstat2-0.1.14.dist-info/licenses/LICENSE
pycircstat2-0.1.14.dist-info/METADATA
pycircstat2-0.1.14.dist-info/WHEEL
pycircstat2-0.1.14.dist-info/top_level.txt
pycircstat2-0.1.14.dist-info/RECORD
