Metadata-Version: 2.4
Name: pycircstat2
Version: 0.1.14
Summary: Circular statistcs with Python.
Requires-Python: >=3.9.0
License-File: LICENSE
Requires-Dist: numpy
Requires-Dist: scipy
Requires-Dist: pandas
Requires-Dist: matplotlib
Provides-Extra: dev
Requires-Dist: ruff; extra == "dev"
Requires-Dist: pytest; extra == "dev"
Requires-Dist: mkdocs; extra == "dev"
Requires-Dist: mkdocs-material-extensions; extra == "dev"
Requires-Dist: mkdocstrings[python]; extra == "dev"
Requires-Dist: watermark; extra == "dev"
Requires-Dist: polars; extra == "dev"
Dynamic: license-file
